{
  "login": {
    "title": "登陆",
    "rightButtonItem": "注册",
    "rightButtonReference": "register",
    "submitPath": "request_new_token",
    "list": [
      {
        "type": "blank",
        "height": 20
      },
      {
        "type": "text_field_with_label",
        "label": "帐号",
        "placeHolder": "请输入邮箱",
        "id": "email"
      },
      {
        "type": "password_field_with_label",
        "label": "密码",
        "placeHolder": "请输入密码",
        "id": "password"
      },
      {
        "type": "annotation",
        "text": "忘记密码",
        "align": "right"
      },
      {
        "type": "block_button",
        "text": "登陆",
        "action": "submit"
      }
    ]
  },
  "register": {
    "title": "注册",
    "rightButtonItem": "",
    "list": [
      {
        "type": "blank",
        "height": 20
      },
      {
        "type": "text_field_with_label",
        "label": "帐号",
        "placeHolder": "请输入邮箱"
      },
      {
        "type": "password_field_with_label",
        "label": "密码",
        "placeHolder": "请输入密码"
      },
      {
        "type": "password_field_with_label",
        "label": "确认",
        "placeHolder": "请再次输入密码"
      },
      {
        "type": "annotation",
        "text": "注册即表示同意xxxxx协议",
        "align": "left"
      },
      {
        "type": "block_button",
        "text": "注册"
      }
    ]
  },
  "userInfo": {
    "title": "基本信息",
    "rightButtonItem": "",
    "list": [
      {
        "type": "avatar",
        "image": "avatar"
      },
      {
        "type": "text_field_with_label_full_width",
        "label": "昵称",
        "placeHolder": "请输入您的昵称"
      },
      {
        "type": "indicator",
        "label": "年龄"
      },
      {
        "type": "indicator",
        "label": "性别"
      },
      {
        "type": "indicator",
        "label": "地区"
      },
      {
        "type": "indicator",
        "label": "年龄"
      },
      {
        "type": "blank",
        "height": 60
      },
      {
        "type": "block_button",
        "text": "确定"
      }
    ]
  }
}
